hdf_compass-0.6.0-py2.7-nspkg.pth
hdf_compass/array_model/__init__.py
hdf_compass/array_model/model.py
hdf_compass/array_model/test.py
hdf_compass/asc_model/__init__.py
hdf_compass/asc_model/model.py
hdf_compass/asc_model/test.py
hdf_compass/bag_model/__init__.py
hdf_compass/bag_model/model.py
hdf_compass/bag_model/test.py
hdf_compass/compass_model/__init__.py
hdf_compass/compass_model/model.py
hdf_compass/compass_model/test.py
hdf_compass/compass_model/icons/array_16.png
hdf_compass/compass_model/icons/array_64.png
hdf_compass/compass_model/icons/folder_16.png
hdf_compass/compass_model/icons/folder_64.png
hdf_compass/compass_model/icons/image_16.png
hdf_compass/compass_model/icons/image_64.png
hdf_compass/compass_model/icons/kv_16.png
hdf_compass/compass_model/icons/kv_64.png
hdf_compass/compass_model/icons/license.txt
hdf_compass/compass_model/icons/readme.txt
hdf_compass/compass_model/icons/text_16.png
hdf_compass/compass_model/icons/text_64.png
hdf_compass/compass_model/icons/unknown_16.png
hdf_compass/compass_model/icons/unknown_64.png
hdf_compass/compass_model/icons/xml_16.png
hdf_compass/compass_model/icons/xml_64.png
hdf_compass/compass_viewer/__init__.py
hdf_compass/compass_viewer/__main__.py
hdf_compass/compass_viewer/events.py
hdf_compass/compass_viewer/frame.py
hdf_compass/compass_viewer/info.py
hdf_compass/compass_viewer/viewer.py
hdf_compass/compass_viewer/array/__init__.py
hdf_compass/compass_viewer/array/frame.py
hdf_compass/compass_viewer/array/plot.py
hdf_compass/compass_viewer/container/__init__.py
hdf_compass/compass_viewer/container/frame.py
hdf_compass/compass_viewer/container/list.py
hdf_compass/compass_viewer/geo_array/__init__.py
hdf_compass/compass_viewer/geo_array/frame.py
hdf_compass/compass_viewer/geo_array/plot.py
hdf_compass/compass_viewer/geo_surface/__init__.py
hdf_compass/compass_viewer/geo_surface/frame.py
hdf_compass/compass_viewer/geo_surface/plot.py
hdf_compass-0.6.0.dist-info/DESCRIPTION.rst
hdf_compass-0.6.0.dist-info/METADATA
hdf_compass-0.6.0.dist-info/RECORD
hdf_compass-0.6.0.dist-info/WHEEL
hdf_compass-0.6.0.dist-info/entry_points.txt
hdf_compass-0.6.0.dist-info/metadata.json
hdf_compass-0.6.0.dist-info/namespace_packages.txt
hdf_compass-0.6.0.dist-info/top_level.txt
