Metadata-Version: 2.0
Name: hdf-compass
Version: 0.6.0
Summary: An experimental viewer program for HDF5 and related formats.
Home-page: https://github.com/HDFGroup/hdf-compass/
Author: HDFGroup
Author-email: help@hdfgroup.org
License: BSD-like license
Keywords: data hdf bag ascii grid opendap
Platform: UNKNOWN
Classifier: Development Status :: 4 - Beta
Classifier: Intended Audience :: Science/Research
Classifier: Natural Language :: English
Classifier: License :: OSI Approved :: BSD License
Classifier: Operating System :: OS Independent
Classifier: Programming Language :: Python
Classifier: Programming Language :: Python :: 2
Classifier: Programming Language :: Python :: 2.7
Classifier: Topic :: Scientific/Engineering :: Information Analysis
Classifier: Topic :: Office/Business :: Office Suites
Classifier: Topic :: Utilities
Requires-Dist: h5py
Requires-Dist: matplotlib (>=1.5)
Requires-Dist: numpy
Requires-Dist: requests
Requires-Dist: wxPython (==3.0.2)
Provides-Extra: BAG
Requires-Dist: hydroffice.bag (>=0.2.10); extra == 'BAG'
Provides-Extra: GeoNodes
Requires-Dist: cartopy[plotting]; extra == 'GeoNodes'
Provides-Extra: OpenDAP
Requires-Dist: pydap; extra == 'OpenDAP'
